{"artist":"DJ Gollum vs. Basslovers United","song":"Narcotic","duration":208.87465,"ts":1712827315969,"sessionId":3775,"auth":"Logged In","level":"paid","itemInSession":26,"city":"Glendale","zip":85304,"state":"AZ","userAgent":"\"Mozilla\/5.0 (X11; Linux x86_64) AppleWebKit\/537.36 (KHTML, like Gecko) Ubuntu Chromium\/34.0.1847.116 Chrome\/34.0.1847.116 Safari\/537.36\"","lon":-112.178276,"lat":33.599739,"userId":16,"lastName":"Liu","firstName":"Aryan","gender":"M","registration":1702889040969,"ts_seconds":1712827315}
{"artist":"Buena Vista Social Club","song":"La Bayamesa","duration":174.28853,"ts":1712827523969,"sessionId":3775,"auth":"Logged In","level":"paid","itemInSession":27,"city":"Glendale","zip":85304,"state":"AZ","userAgent":"\"Mozilla\/5.0 (X11; Linux x86_64) AppleWebKit\/537.36 (KHTML, like Gecko) Ubuntu Chromium\/34.0.1847.116 Chrome\/34.0.1847.116 Safari\/537.36\"","lon":-112.178276,"lat":33.599739,"userId":16,"lastName":"Liu","firstName":"Aryan","gender":"M","registration":1702889040969,"ts_seconds":1712827523}
{"artist":"Threshold","song":"Light and space","duration":358.4779,"ts":1712827697969,"sessionId":3775,"auth":"Logged In","level":"paid","itemInSession":28,"city":"Glendale","zip":85304,"state":"AZ","userAgent":"\"Mozilla\/5.0 (X11; Linux x86_64) AppleWebKit\/537.36 (KHTML, like Gecko) Ubuntu Chromium\/34.0.1847.116 Chrome\/34.0.1847.116 Safari\/537.36\"","lon":-112.178276,"lat":33.599739,"userId":16,"lastName":"Liu","firstName":"Aryan","gender":"M","registration":1702889040969,"ts_seconds":1712827697}
{"artist":"Brandy","song":"Best Friend ( LP Version )","duration":288.6265,"ts":1712828055969,"sessionId":3775,"auth":"Logged In","level":"paid","itemInSession":29,"city":"Glendale","zip":85304,"state":"AZ","userAgent":"\"Mozilla\/5.0 (X11; Linux x86_64) AppleWebKit\/537.36 (KHTML, like Gecko) Ubuntu Chromium\/34.0.1847.116 Chrome\/34.0.1847.116 Safari\/537.36\"","lon":-112.178276,"lat":33.599739,"userId":16,"lastName":"Liu","firstName":"Aryan","gender":"M","registration":1702889040969,"ts_seconds":1712828055}
{"artist":"L7","song":"Pretend We're Dead","duration":235.1016,"ts":1712828343969,"sessionId":3775,"auth":"Logged In","level":"paid","itemInSession":30,"city":"Glendale","zip":85304,"state":"AZ","userAgent":"\"Mozilla\/5.0 (X11; Linux x86_64) AppleWebKit\/537.36 (KHTML, like Gecko) Ubuntu Chromium\/34.0.1847.116 Chrome\/34.0.1847.116 Safari\/537.36\"","lon":-112.178276,"lat":33.599739,"userId":16,"lastName":"Liu","firstName":"Aryan","gender":"M","registration":1702889040969,"ts_seconds":1712828343}
{"artist":"P.O.D.","song":"Youth Of The Nation (2006 Remastered Album Version)","duration":258.16772,"ts":1712828552969,"sessionId":3801,"auth":"Logged In","level":"free","itemInSession":1,"city":"Flippin","zip":72634,"state":"AR","userAgent":"\"Mozilla\/5.0 (Windows NT 6.1; WOW64) AppleWebKit\/537.36 (KHTML, like Gecko) Chrome\/37.0.2062.103 Safari\/537.36\"","lon":-92.513515,"lat":36.200113,"userId":95,"lastName":"Romero","firstName":"Noah","gender":"M","registration":1703531539969,"ts_seconds":1712828552}
{"artist":"Arcade Fire","song":"I'm Sleeping In A Submarine","duration":169.19466,"ts":1712828578969,"sessionId":3775,"auth":"Logged In","level":"paid","itemInSession":31,"city":"Glendale","zip":85304,"state":"AZ","userAgent":"\"Mozilla\/5.0 (X11; Linux x86_64) AppleWebKit\/537.36 (KHTML, like Gecko) Ubuntu Chromium\/34.0.1847.116 Chrome\/34.0.1847.116 Safari\/537.36\"","lon":-112.178276,"lat":33.599739,"userId":16,"lastName":"Liu","firstName":"Aryan","gender":"M","registration":1702889040969,"ts_seconds":1712828578}
{"artist":"Assemblage 23","song":"LULLABY","duration":324.33588,"ts":1712828747969,"sessionId":3775,"auth":"Logged In","level":"paid","itemInSession":32,"city":"Glendale","zip":85304,"state":"AZ","userAgent":"\"Mozilla\/5.0 (X11; Linux x86_64) AppleWebKit\/537.36 (KHTML, like Gecko) Ubuntu Chromium\/34.0.1847.116 Chrome\/34.0.1847.116 Safari\/537.36\"","lon":-112.178276,"lat":33.599739,"userId":16,"lastName":"Liu","firstName":"Aryan","gender":"M","registration":1702889040969,"ts_seconds":1712828747}
{"artist":"Tears For Fears","song":"Raoul and The Kings of Spain","duration":315.48035,"ts":1712828810969,"sessionId":3801,"auth":"Logged In","level":"free","itemInSession":2,"city":"Flippin","zip":72634,"state":"AR","userAgent":"\"Mozilla\/5.0 (Windows NT 6.1; WOW64) AppleWebKit\/537.36 (KHTML, like Gecko) Chrome\/37.0.2062.103 Safari\/537.36\"","lon":-92.513515,"lat":36.200113,"userId":95,"lastName":"Romero","firstName":"Noah","gender":"M","registration":1703531539969,"ts_seconds":1712828810}
{"artist":"Bad Brains","song":"The Regulator","duration":68.85832,"ts":1712829071969,"sessionId":3775,"auth":"Logged In","level":"paid","itemInSession":33,"city":"Glendale","zip":85304,"state":"AZ","userAgent":"\"Mozilla\/5.0 (X11; Linux x86_64) AppleWebKit\/537.36 (KHTML, like Gecko) Ubuntu Chromium\/34.0.1847.116 Chrome\/34.0.1847.116 Safari\/537.36\"","lon":-112.178276,"lat":33.599739,"userId":16,"lastName":"Liu","firstName":"Aryan","gender":"M","registration":1702889040969,"ts_seconds":1712829071}
{"artist":"Margot & The Nuclear So And So's","song":"Dress Me Like a Clown","duration":276.79303,"ts":1712829125969,"sessionId":3801,"auth":"Logged In","level":"free","itemInSession":3,"city":"Flippin","zip":72634,"state":"AR","userAgent":"\"Mozilla\/5.0 (Windows NT 6.1; WOW64) AppleWebKit\/537.36 (KHTML, like Gecko) Chrome\/37.0.2062.103 Safari\/537.36\"","lon":-92.513515,"lat":36.200113,"userId":95,"lastName":"Romero","firstName":"Noah","gender":"M","registration":1703531539969,"ts_seconds":1712829125}
{"artist":"Erin McKeown","song":"Blackbirds","duration":265.273,"ts":1712829139969,"sessionId":3775,"auth":"Logged In","level":"paid","itemInSession":34,"city":"Glendale","zip":85304,"state":"AZ","userAgent":"\"Mozilla\/5.0 (X11; Linux x86_64) AppleWebKit\/537.36 (KHTML, like Gecko) Ubuntu Chromium\/34.0.1847.116 Chrome\/34.0.1847.116 Safari\/537.36\"","lon":-112.178276,"lat":33.599739,"userId":16,"lastName":"Liu","firstName":"Aryan","gender":"M","registration":1702889040969,"ts_seconds":1712829139}
{"artist":"Jimmy Eat World","song":"The Middle","duration":166.0077,"ts":1712833719969,"sessionId":3645,"auth":"Logged In","level":"paid","itemInSession":0,"city":"Schenectady","zip":12303,"state":"NY","userAgent":"\"Mozilla\/5.0 (X11; Linux x86_64) AppleWebKit\/537.36 (KHTML, like Gecko) Ubuntu Chromium\/36.0.1985.125 Chrome\/36.0.1985.125 Safari\/537.36\"","lon":-73.926481,"lat":42.753534,"userId":51,"lastName":"Davidson","firstName":"Emily","gender":"F","registration":1703584078969,"ts_seconds":1712833719}
{"artist":"The Yardbirds","song":"I Wish You Would","duration":356.88443,"ts":1712833885969,"sessionId":3645,"auth":"Logged In","level":"paid","itemInSession":1,"city":"Schenectady","zip":12303,"state":"NY","userAgent":"\"Mozilla\/5.0 (X11; Linux x86_64) AppleWebKit\/537.36 (KHTML, like Gecko) Ubuntu Chromium\/36.0.1985.125 Chrome\/36.0.1985.125 Safari\/537.36\"","lon":-73.926481,"lat":42.753534,"userId":51,"lastName":"Davidson","firstName":"Emily","gender":"F","registration":1703584078969,"ts_seconds":1712833885}
{"artist":"Heavy","song":"Wonderlove","duration":338.25912,"ts":1712833896969,"sessionId":3680,"auth":"Logged In","level":"free","itemInSession":1,"city":"Redmond","zip":97756,"state":"OR","userAgent":"Mozilla\/5.0 (compatible; MSIE 10.0; Windows NT 6.1; WOW64; Trident\/6.0)","lon":-121.216724,"lat":44.283326,"userId":46,"lastName":"Moon","firstName":"Derriona","gender":"F","registration":1703499187969,"ts_seconds":1712833896}
{"artist":"Aaliyah","song":"Are You That Somebody? ( LP Version )","duration":266.50076,"ts":1712834241969,"sessionId":3645,"auth":"Logged In","level":"paid","itemInSession":2,"city":"Schenectady","zip":12303,"state":"NY","userAgent":"\"Mozilla\/5.0 (X11; Linux x86_64) AppleWebKit\/537.36 (KHTML, like Gecko) Ubuntu Chromium\/36.0.1985.125 Chrome\/36.0.1985.125 Safari\/537.36\"","lon":-73.926481,"lat":42.753534,"userId":51,"lastName":"Davidson","firstName":"Emily","gender":"F","registration":1703584078969,"ts_seconds":1712834241}
{"artist":"Mal\u00c3\u0083\u00c2\u00ba","song":"Me Qued\u00c3\u0083\u00c2\u00b3 Grande Tu Amor","duration":272.5612,"ts":1712834507969,"sessionId":3645,"auth":"Logged In","level":"paid","itemInSession":3,"city":"Schenectady","zip":12303,"state":"NY","userAgent":"\"Mozilla\/5.0 (X11; Linux x86_64) AppleWebKit\/537.36 (KHTML, like Gecko) Ubuntu Chromium\/36.0.1985.125 Chrome\/36.0.1985.125 Safari\/537.36\"","lon":-73.926481,"lat":42.753534,"userId":51,"lastName":"Davidson","firstName":"Emily","gender":"F","registration":1703584078969,"ts_seconds":1712834507}
{"artist":"Aeon","song":"Of Fire","duration":245.44608,"ts":1712834779969,"sessionId":3645,"auth":"Logged In","level":"paid","itemInSession":4,"city":"Schenectady","zip":12303,"state":"NY","userAgent":"\"Mozilla\/5.0 (X11; Linux x86_64) AppleWebKit\/537.36 (KHTML, like Gecko) Ubuntu Chromium\/36.0.1985.125 Chrome\/36.0.1985.125 Safari\/537.36\"","lon":-73.926481,"lat":42.753534,"userId":51,"lastName":"Davidson","firstName":"Emily","gender":"F","registration":1703584078969,"ts_seconds":1712834779}
