{"artist":"Angels and Airwaves","song":"Breathe","duration":333.58322,"ts":1709342553969,"sessionId":2390,"auth":"Logged In","level":"paid","itemInSession":72,"city":"Old Orchard Beach","zip":4064,"state":"ME","userAgent":"\"Mozilla\/5.0 (Macintosh; Intel Mac OS X 10_9_4) AppleWebKit\/537.77.4 (KHTML, like Gecko) Version\/7.0.5 Safari\/537.77.4\"","lon":-70.38825,"lat":43.525044,"userId":15,"lastName":"Stewart","firstName":"Dakota","gender":"F","registration":1703545426969,"ts_seconds":1709342553}
{"artist":"Gold Panda","song":"You","duration":229.69424,"ts":1709342886969,"sessionId":2390,"auth":"Logged In","level":"paid","itemInSession":73,"city":"Old Orchard Beach","zip":4064,"state":"ME","userAgent":"\"Mozilla\/5.0 (Macintosh; Intel Mac OS X 10_9_4) AppleWebKit\/537.77.4 (KHTML, like Gecko) Version\/7.0.5 Safari\/537.77.4\"","lon":-70.38825,"lat":43.525044,"userId":15,"lastName":"Stewart","firstName":"Dakota","gender":"F","registration":1703545426969,"ts_seconds":1709342886}
{"artist":"Lonnie Gordon","song":"Catch You Baby (Steve Pitron & Max Sanna Radio Edit)","duration":181.21098,"ts":1709343115969,"sessionId":2390,"auth":"Logged In","level":"paid","itemInSession":74,"city":"Old Orchard Beach","zip":4064,"state":"ME","userAgent":"\"Mozilla\/5.0 (Macintosh; Intel Mac OS X 10_9_4) AppleWebKit\/537.77.4 (KHTML, like Gecko) Version\/7.0.5 Safari\/537.77.4\"","lon":-70.38825,"lat":43.525044,"userId":15,"lastName":"Stewart","firstName":"Dakota","gender":"F","registration":1703545426969,"ts_seconds":1709343115}
{"artist":"Julie London","song":"You'd Be So Nice To Come Home To","duration":136.5416,"ts":1709343296969,"sessionId":2390,"auth":"Logged In","level":"paid","itemInSession":75,"city":"Old Orchard Beach","zip":4064,"state":"ME","userAgent":"\"Mozilla\/5.0 (Macintosh; Intel Mac OS X 10_9_4) AppleWebKit\/537.77.4 (KHTML, like Gecko) Version\/7.0.5 Safari\/537.77.4\"","lon":-70.38825,"lat":43.525044,"userId":15,"lastName":"Stewart","firstName":"Dakota","gender":"F","registration":1703545426969,"ts_seconds":1709343296}
{"artist":"VHS Or Beta","song":"We Could Be One","duration":310.90894,"ts":1709344875969,"sessionId":2417,"auth":"Logged In","level":"paid","itemInSession":0,"city":"Colorado Springs","zip":80906,"state":"CO","userAgent":"Mozilla\/5.0 (Macintosh; Intel Mac OS X 10.9; rv:31.0) Gecko\/20100101 Firefox\/31.0","lon":-104.878195,"lat":38.752622,"userId":41,"lastName":"Alexander","firstName":"Alli","gender":"F","registration":1703586077969,"ts_seconds":1709344875}
{"artist":"Dwight Yoakam","song":"You're The One","duration":239.3073,"ts":1709347857969,"sessionId":2277,"auth":"Logged In","level":"free","itemInSession":0,"city":"Danvers","zip":1923,"state":"MA","userAgent":"\"Mozilla\/5.0 (Windows NT 6.1; WOW64) AppleWebKit\/537.36 (KHTML, like Gecko) Chrome\/36.0.1985.125 Safari\/537.36\"","lon":-70.950516,"lat":42.574174,"userId":5,"lastName":"Davis","firstName":"Elijah","gender":"M","registration":1703344332969,"ts_seconds":1709347857}
{"artist":"Muse","song":"Unnatural Selection","duration":414.95465,"ts":1709348096969,"sessionId":2277,"auth":"Logged In","level":"free","itemInSession":1,"city":"Danvers","zip":1923,"state":"MA","userAgent":"\"Mozilla\/5.0 (Windows NT 6.1; WOW64) AppleWebKit\/537.36 (KHTML, like Gecko) Chrome\/36.0.1985.125 Safari\/537.36\"","lon":-70.950516,"lat":42.574174,"userId":5,"lastName":"Davis","firstName":"Elijah","gender":"M","registration":1703344332969,"ts_seconds":1709348096}
{"artist":"Lily Allen","song":"Never Gonna Happen","duration":207.35954,"ts":1709348129969,"sessionId":2368,"auth":"Logged In","level":"free","itemInSession":0,"city":"Houston","zip":77057,"state":"TX","userAgent":"Mozilla\/5.0 (Windows NT 6.1; WOW64; rv:24.0) Gecko\/20100101 Firefox\/24.0","lon":-95.487974,"lat":29.744081,"userId":34,"lastName":"Jackson","firstName":"Alexander","gender":"M","registration":1702860264969,"ts_seconds":1709348129}
{"artist":"Blockhead","song":"Attack The Doctor","duration":346.43546,"ts":1709348336969,"sessionId":2368,"auth":"Logged In","level":"free","itemInSession":1,"city":"Houston","zip":77057,"state":"TX","userAgent":"Mozilla\/5.0 (Windows NT 6.1; WOW64; rv:24.0) Gecko\/20100101 Firefox\/24.0","lon":-95.487974,"lat":29.744081,"userId":34,"lastName":"Jackson","firstName":"Alexander","gender":"M","registration":1702860264969,"ts_seconds":1709348336}
{"artist":"Kansas","song":"Paradox","duration":246.12526,"ts":1709348510969,"sessionId":2277,"auth":"Logged In","level":"free","itemInSession":2,"city":"Danvers","zip":1923,"state":"MA","userAgent":"\"Mozilla\/5.0 (Windows NT 6.1; WOW64) AppleWebKit\/537.36 (KHTML, like Gecko) Chrome\/36.0.1985.125 Safari\/537.36\"","lon":-70.950516,"lat":42.574174,"userId":5,"lastName":"Davis","firstName":"Elijah","gender":"M","registration":1703344332969,"ts_seconds":1709348510}
{"artist":"Starfield","song":"Filled With Your Glory (Prelude)","duration":37.642,"ts":1709348682969,"sessionId":2368,"auth":"Logged In","level":"free","itemInSession":2,"city":"Houston","zip":77057,"state":"TX","userAgent":"Mozilla\/5.0 (Windows NT 6.1; WOW64; rv:24.0) Gecko\/20100101 Firefox\/24.0","lon":-95.487974,"lat":29.744081,"userId":34,"lastName":"Jackson","firstName":"Alexander","gender":"M","registration":1702860264969,"ts_seconds":1709348682}
{"artist":"Beck","song":"Beautiful Way","duration":335.46405,"ts":1709348719969,"sessionId":2368,"auth":"Logged In","level":"free","itemInSession":3,"city":"Houston","zip":77057,"state":"TX","userAgent":"Mozilla\/5.0 (Windows NT 6.1; WOW64; rv:24.0) Gecko\/20100101 Firefox\/24.0","lon":-95.487974,"lat":29.744081,"userId":34,"lastName":"Jackson","firstName":"Alexander","gender":"M","registration":1702860264969,"ts_seconds":1709348719}
{"artist":"Counting Crows","song":"Mr. Jones","duration":272.7963,"ts":1709348756969,"sessionId":2277,"auth":"Logged In","level":"free","itemInSession":3,"city":"Danvers","zip":1923,"state":"MA","userAgent":"\"Mozilla\/5.0 (Windows NT 6.1; WOW64) AppleWebKit\/537.36 (KHTML, like Gecko) Chrome\/36.0.1985.125 Safari\/537.36\"","lon":-70.950516,"lat":42.574174,"userId":5,"lastName":"Davis","firstName":"Elijah","gender":"M","registration":1703344332969,"ts_seconds":1709348756}
{"artist":"Lole y Manuel","song":"Tu Mira (Edit)","duration":239.46404,"ts":1709349054969,"sessionId":2368,"auth":"Logged In","level":"free","itemInSession":4,"city":"Houston","zip":77057,"state":"TX","userAgent":"Mozilla\/5.0 (Windows NT 6.1; WOW64; rv:24.0) Gecko\/20100101 Firefox\/24.0","lon":-95.487974,"lat":29.744081,"userId":34,"lastName":"Jackson","firstName":"Alexander","gender":"M","registration":1702860264969,"ts_seconds":1709349054}
{"artist":"The Highwaymen (Waylon Jennings_ Willie Nelson_ Johnny Cash_ Kris Kristofferson)","song":"Highwayman","duration":183.71873,"ts":1709366183969,"sessionId":2363,"auth":"Logged In","level":"free","itemInSession":1,"city":"Forney","zip":75126,"state":"TX","userAgent":"\"Mozilla\/5.0 (Macintosh; Intel Mac OS X 10_10) AppleWebKit\/600.1.3 (KHTML, like Gecko) Version\/8.0 Safari\/600.1.3\"","lon":-96.4549,"lat":32.743178,"userId":88,"lastName":"Bond","firstName":"Kaiden","gender":"M","registration":1703594237969,"ts_seconds":1709366183}
{"artist":"Kate Nash","song":"Merry Happy \/ Little Red","duration":790.282,"ts":1709366366969,"sessionId":2363,"auth":"Logged In","level":"free","itemInSession":2,"city":"Forney","zip":75126,"state":"TX","userAgent":"\"Mozilla\/5.0 (Macintosh; Intel Mac OS X 10_10) AppleWebKit\/600.1.3 (KHTML, like Gecko) Version\/8.0 Safari\/600.1.3\"","lon":-96.4549,"lat":32.743178,"userId":88,"lastName":"Bond","firstName":"Kaiden","gender":"M","registration":1703594237969,"ts_seconds":1709366366}
{"artist":"Alexi Murdoch","song":"Orange Sky","duration":371.1473,"ts":1709366688969,"sessionId":2438,"auth":"Logged In","level":"paid","itemInSession":0,"city":"Prosperity","zip":29127,"state":"SC","userAgent":"Mozilla\/5.0 (Windows NT 6.0; rv:31.0) Gecko\/20100101 Firefox\/31.0","lon":-81.512463,"lat":34.153252,"userId":77,"lastName":"Russell","firstName":"Mycah","gender":"M","registration":1703597623969,"ts_seconds":1709366688}
